zerojs/__init__.py
zerojs/app.py
zerojs/cache.py
zerojs/constants.py
zerojs/context.py
zerojs/csrf.py
zerojs/decorators.py
zerojs/forms.py
zerojs/handlers.py
zerojs/py.typed
zerojs/renderer.py
zerojs/response.py
zerojs/router.py
zerojs/settings.py
zerojs/types.py
zerojs/validation.py
zerojs/auth/__init__.py
zerojs/auth/authenticator.py
zerojs/auth/context.py
zerojs/auth/decorators.py
zerojs/auth/events.py
zerojs/auth/exceptions.py
zerojs/auth/handlers.py
zerojs/auth/mfa.py
zerojs/auth/middleware.py
zerojs/auth/passwords.py
zerojs/auth/protocols.py
zerojs/auth/rate_limit.py
zerojs/auth/session_adapter.py
zerojs/auth/testing.py
zerojs/auth/tokens.py
zerojs/auth/permissions/__init__.py
zerojs/auth/permissions/abac.py
zerojs/auth/permissions/backend.py
zerojs/auth/permissions/rbac.py
zerojs/middleware/__init__.py
zerojs/routes/__init__.py
zerojs/routes/components.py
zerojs/routes/pages.py
zerojs/security/__init__.py
zerojs/security/path_travesal_protection.py
zerojs/session/__init__.py
zerojs/session/cookies.py
zerojs/session/data.py
zerojs/session/exceptions.py
zerojs/session/middleware.py
zerojs/session/storage.py
zerojs/session/backends/__init__.py
zerojs/session/backends/file.py
zerojs/session/backends/memory.py
zerojs/session/backends/redis.py
zerojs/templates/zerojs/base.html
zerojs/templates/zerojs/components/form.shadow.html
zerojs-0.3.0.dist-info/METADATA
zerojs-0.3.0.dist-info/WHEEL
zerojs-0.3.0.dist-info/licenses/LICENSE
zerojs-0.3.0.dist-info/RECORD
