Metadata-Version: 2.4
Name: zerojs
Version: 0.3.0
Summary: Modern frontend capabilities for Python developers — no JavaScript required
Project-URL: Homepage, https://zerojs.dev
Project-URL: Documentation, https://zerojs.dev
Project-URL: Repository, https://github.com/kennylajara/zerojs
Project-URL: Issues, https://github.com/kennylajara/zerojs/issues
Author-email: Kenny Lajara <kennylajara@gmail.com>
License-Expression: Apache-2.0
License-File: LICENSE
Keywords: fastapi,framework,frontend,htmx,jinja2,no-javascript,pyscript,web
Classifier: Development Status :: 3 - Alpha
Classifier: Environment :: Web Environment
Classifier: Framework :: FastAPI
Classifier: Intended Audience :: Developers
Classifier: License :: OSI Approved :: Apache Software License
Classifier: Operating System :: OS Independent
Classifier: Programming Language :: Python :: 3
Classifier: Programming Language :: Python :: 3.10
Classifier: Programming Language :: Python :: 3.11
Classifier: Programming Language :: Python :: 3.12
Classifier: Programming Language :: Python :: 3.13
Classifier: Programming Language :: Python :: 3.14
Classifier: Topic :: Internet :: WWW/HTTP
Classifier: Topic :: Software Development :: Libraries :: Python Modules
Classifier: Typing :: Typed
Requires-Python: >=3.10
Requires-Dist: email-validator>=2.3.0
Requires-Dist: fastapi>=0.128.0
Requires-Dist: itsdangerous>=2.2.0
Requires-Dist: jinja2>=3.1.6
Requires-Dist: python-multipart>=0.0.21
Requires-Dist: secweb>=1.11.0
Requires-Dist: slowapi>=0.1.9
Requires-Dist: uvicorn>=0.40.0
Provides-Extra: auth
Requires-Dist: argon2-cffi>=23.1.0; extra == 'auth'
Requires-Dist: bcrypt>=4.2.0; extra == 'auth'
Provides-Extra: dev
Requires-Dist: watchfiles>=1.0.0; extra == 'dev'
